jrdb_model/__init__.py
jrdb_model/sessioncontroll.py
jrdb_model/domain/__init__.py
jrdb_model/domain/bangumi.py
jrdb_model/domain/calculated_score.py
jrdb_model/domain/kaisai.py
jrdb_model/domain/predict.py
jrdb_model/domain/predict_race.py
jrdb_model/domain/racehorse.py
jrdb_model/domain/returninfo.py
jrdb_model/domain/seiseki.py
jrdb_model/domain/seisekirace.py
jrdb_model/domain/trainanalysis.py
jrdb_model/domain/trainoikiri.py
jrdb_model/domain/umaren_odds.py
jrdb_model/domain/wakuren_odds.py
jrdb_model/domain/wide_odds.py
jrdb_model/master/__init__.py
jrdb_model/master/horsebase.py
jrdb_model/master/jockey.py
jrdb_model/master/mastercode.py
jrdb_model/master/trainer.py
jrdb_model-0.2.10.dist-info/licenses/LICENSE
jrdb_model-0.2.10.dist-info/METADATA
jrdb_model-0.2.10.dist-info/WHEEL
jrdb_model-0.2.10.dist-info/top_level.txt
jrdb_model-0.2.10.dist-info/RECORD
