Metadata-Version: 2.4
Name: jrdb-model
Version: 0.2.10
Summary: ORM for JRDB
Author-email: requrd <requrd1989@gmail.com>
Project-URL: Bug Tracker, https://github.com/astroripple/horseview/issues
Project-URL: Homepage, https://github.com/astroripple/horseview
Classifier: Programming Language :: Python :: 3
Classifier: License :: OSI Approved :: MIT License
Classifier: Operating System :: OS Independent
License-File: LICENSE
Requires-Dist: flask-migrate>=4.1.0
Requires-Dist: pymysql>=1.1.1
Dynamic: license-file
